django_phone_verify-3.3.0.dist-info/licenses/LICENSE
phone_verify/MANIFEST.in
phone_verify/__init__.py
phone_verify/admin.py
phone_verify/api.py
phone_verify/apps.py
phone_verify/constants.py
phone_verify/models.py
phone_verify/serializers.py
phone_verify/services.py
phone_verify/urls.py
phone_verify/backends/__init__.py
phone_verify/backends/base.py
phone_verify/backends/nexmo.py
phone_verify/backends/twilio.py
phone_verify/base/__init__.py
phone_verify/base/response.py
phone_verify/docs/api_endpoints.rst
phone_verify/management/__init__.py
phone_verify/management/commands/__init__.py
phone_verify/management/commands/cleanup_phone_verifications.py
phone_verify/migrations/0001_initial.py
phone_verify/migrations/0002_auto_20190817_1753.py
phone_verify/migrations/0003_smsverification_failed_attempts.py
phone_verify/migrations/__init__.py
django_phone_verify-3.3.0.dist-info/METADATA
django_phone_verify-3.3.0.dist-info/WHEEL
django_phone_verify-3.3.0.dist-info/top_level.txt
django_phone_verify-3.3.0.dist-info/RECORD
