Metadata-Version: 2.4
Name: django-phone-verify
Version: 3.3.0
Summary: A Django app to support phone number verification using security code sent via SMS.
Home-page: https://github.com/CuriousLearner/django-phone-verify
Author: Sanyam Khurana
Author-email: Sanyam Khurana <sanyam@sanyamkhurana.com>
License: GPLv3
Project-URL: Documentation, https://django-phone-verify.readthedocs.io/
Project-URL: Changelog, https://github.com/CuriousLearner/django-phone-verify/blob/master/CHANGELOG.rst
Project-URL: Code, https://github.com/CuriousLearner/django-phone-verify
Project-URL: Homepage, https://github.com/CuriousLearner/django-phone-verify
Project-URL: Tracker, https://github.com/CuriousLearner/django-phone-verify/issues
Project-URL: Funding, https://github.com/sponsors/CuriousLearner
Keywords: django,phone,verification,SMS,twilio,nexmo,vonage,OTP,2FA,authentication
Classifier: Environment :: Web Environment
Classifier: Development Status :: 5 - Production/Stable
Classifier: Framework :: Django
Classifier: Framework :: Django :: 2.0
Classifier: Framework :: Django :: 2.1
Classifier: Framework :: Django :: 2.2
Classifier: Framework :: Django :: 3.0
Classifier: Framework :: Django :: 3.1
Classifier: Framework :: Django :: 3.2
Classifier: Framework :: Django :: 4.0
Classifier: Framework :: Django :: 4.1
Classifier: Framework :: Django :: 4.2
Classifier: Framework :: Django :: 5.0
Classifier: Framework :: Django :: 5.1
Classifier: Framework :: Django :: 5.2
Classifier: Framework :: Django :: 6.0
Classifier: Intended Audience :: Developers
Classifier: License :: OSI Approved :: GNU General Public License v3 (GPLv3)
Classifier: Operating System :: OS Independent
Classifier: Programming Language :: Python
Classifier: Programming Language :: Python :: 3.8
Classifier: Programming Language :: Python :: 3.9
Classifier: Programming Language :: Python :: 3.10
Classifier: Programming Language :: Python :: 3.11
Classifier: Programming Language :: Python :: 3.12
Classifier: Programming Language :: Python :: 3.13
Classifier: Programming Language :: Python :: 3.14
Classifier: Topic :: Internet :: WWW/HTTP
Classifier: Topic :: Internet :: WWW/HTTP :: Dynamic Content
Requires-Python: >=3.8
License-File: LICENSE
Requires-Dist: django>=2.1.5
Requires-Dist: djangorestframework>=3.9.0
Requires-Dist: PyJWT>=2.6.0
Requires-Dist: python-dotenv>=0.21.1
Requires-Dist: phonenumberslite>=9.0.1
Requires-Dist: django-phonenumber-field>=2.1.0
Provides-Extra: twilio
Requires-Dist: twilio; extra == "twilio"
Provides-Extra: nexmo
Requires-Dist: nexmo; extra == "nexmo"
Provides-Extra: all
Requires-Dist: twilio; extra == "all"
Requires-Dist: nexmo; extra == "all"
Dynamic: author
Dynamic: home-page
Dynamic: license-file
Dynamic: requires-python
